zope/app/authentication/README.rst
zope/app/authentication/__init__.py
zope/app/authentication/authentication.py
zope/app/authentication/configure.zcml
zope/app/authentication/ftesting.zcml
zope/app/authentication/ftpplugins.py
zope/app/authentication/ftpplugins.zcml
zope/app/authentication/generic.py
zope/app/authentication/groupfolder.py
zope/app/authentication/groupfolder.rst
zope/app/authentication/groupfolder.zcml
zope/app/authentication/httpplugins.py
zope/app/authentication/httpplugins.zcml
zope/app/authentication/i18n.py
zope/app/authentication/idpicker.py
zope/app/authentication/interfaces.py
zope/app/authentication/password.py
zope/app/authentication/password.zcml
zope/app/authentication/placelesssetup.py
zope/app/authentication/principalfolder.py
zope/app/authentication/principalfolder.rst
zope/app/authentication/principalfolder.zcml
zope/app/authentication/session.py
zope/app/authentication/session.zcml
zope/app/authentication/testing.py
zope/app/authentication/tests.py
zope/app/authentication/vocabulary.py
zope/app/authentication/vocabulary.rst
zope/app/authentication/browser/__init__.py
zope/app/authentication/browser/adding.py
zope/app/authentication/browser/configure.zcml
zope/app/authentication/browser/grant.zcml
zope/app/authentication/browser/granting.pt
zope/app/authentication/browser/granting.py
zope/app/authentication/browser/granting.rst
zope/app/authentication/browser/group_searching_with_empty_string.rst
zope/app/authentication/browser/groupfolder.rst
zope/app/authentication/browser/groupfolder.zcml
zope/app/authentication/browser/httpplugins.zcml
zope/app/authentication/browser/issue663.rst
zope/app/authentication/browser/loginform.pt
zope/app/authentication/browser/loginform.py
zope/app/authentication/browser/manage_access.pt
zope/app/authentication/browser/manage_permissionform.pt
zope/app/authentication/browser/manage_roleform.pt
zope/app/authentication/browser/pau_prefix_and_searching.rst
zope_app_authentication-6.0.dist-info/licenses/LICENSE.txt
zope_app_authentication-6.0.dist-info/METADATA
zope_app_authentication-6.0.dist-info/WHEEL
zope_app_authentication-6.0.dist-info/top_level.txt
zope_app_authentication-6.0.dist-info/RECORD
