Metadata-Version: 2.4
Name: zope.app.authentication
Version: 6.0
Summary: Principals and groups management for the pluggable authentication utility
Home-page: http://github.com/zopefoundation/zope.app.authentication
Author: Zope Foundation and Contributors
Author-email: zope-dev@zope.dev
License: ZPL-2.1
Keywords: zope3 authentication pluggable principal group
Classifier: Development Status :: 5 - Production/Stable
Classifier: Environment :: Web Environment
Classifier: Intended Audience :: Developers
Classifier: License :: OSI Approved :: Zope Public License
Classifier: Programming Language :: Python
Classifier: Programming Language :: Python :: 3
Classifier: Programming Language :: Python :: 3.9
Classifier: Programming Language :: Python :: 3.10
Classifier: Programming Language :: Python :: 3.11
Classifier: Programming Language :: Python :: 3.12
Classifier: Programming Language :: Python :: 3.13
Classifier: Programming Language :: Python :: Implementation
Classifier: Programming Language :: Python :: Implementation :: CPython
Classifier: Programming Language :: Python :: Implementation :: PyPy
Classifier: Natural Language :: English
Classifier: Operating System :: OS Independent
Classifier: Topic :: Internet :: WWW/HTTP
Classifier: Framework :: Zope :: 3
Requires-Python: >=3.9
License-File: LICENSE.txt
Requires-Dist: setuptools
Requires-Dist: zope.authentication
Requires-Dist: zope.component
Requires-Dist: zope.container
Requires-Dist: zope.dublincore
Requires-Dist: zope.event
Requires-Dist: zope.exceptions
Requires-Dist: zope.formlib>=4.0.2
Requires-Dist: zope.i18n
Requires-Dist: zope.i18nmessageid
Requires-Dist: zope.interface
Requires-Dist: zope.location
Requires-Dist: zope.password>=3.5.1
Requires-Dist: zope.pluggableauth>=2.2.0
Requires-Dist: zope.schema
Requires-Dist: zope.security
Requires-Dist: zope.traversing
Requires-Dist: zope.app.container>=4.0.0
Requires-Dist: zope.app.component>=4.0.0
Provides-Extra: test
Requires-Dist: zope.app.security>=4.0; extra == "test"
Requires-Dist: zope.app.rotterdam>=4.0; extra == "test"
Requires-Dist: zope.app.basicskin>=4.0; extra == "test"
Requires-Dist: zope.app.form>=5.0; extra == "test"
Requires-Dist: zope.app.wsgi[testlayer]>=5.3; extra == "test"
Requires-Dist: zope.app.schema; extra == "test"
Requires-Dist: zope.formlib; extra == "test"
Requires-Dist: zope.login; extra == "test"
Requires-Dist: zope.principalannotation; extra == "test"
Requires-Dist: zope.publisher>=4.3.1; extra == "test"
Requires-Dist: zope.publisher; extra == "test"
Requires-Dist: zope.securitypolicy; extra == "test"
Requires-Dist: zope.session; extra == "test"
Requires-Dist: zope.site; extra == "test"
Requires-Dist: zope.testbrowser>=5.2; extra == "test"
Requires-Dist: zope.testing; extra == "test"
Requires-Dist: zope.testrunner>=6.4; extra == "test"
Dynamic: author
Dynamic: author-email
Dynamic: classifier
Dynamic: description
Dynamic: home-page
Dynamic: keywords
Dynamic: license
Dynamic: license-file
Dynamic: provides-extra
Dynamic: requires-dist
Dynamic: requires-python
Dynamic: summary
